citools/console.py
citools/dump_failures.py
citools/test_triage_bug_filer.py
mozci_tools-0.1.0.dist-info/entry_points.txt
mozci_tools-0.1.0.dist-info/LICENSE
mozci_tools-0.1.0.dist-info/WHEEL
mozci_tools-0.1.0.dist-info/METADATA
mozci_tools-0.1.0.dist-info/RECORD
